{
  "posts": [
    {
      "title": "V",
      "movieDescription": "V",
      "movieThoughts": "H",
      "rating": 1,
      "id": "d0eb"
    },
    {
      "title": "Movie Name",
      "movieDescription": "Description",
      "movieThoughts": "It was okay ",
      "rating": 3,
      "id": "2075"
    },
    {
      "title": "Hello Everyone",
      "movieDescription": "This is the description",
      "movieThoughts": "This are my thought ",
      "rating": 4,
      "id": "7158"
    },
    {
      "id": "a26e",
      "title": "",
      "movieDescription": "",
      "movieThoughts": "",
      "rating": 5
    },
    {
      "id": "4ebe",
      "title": "",
      "movieDescription": "",
      "movieThoughts": "",
      "rating": 0
    }
  ]
}